MANIFEST.in
requirements.txt
setup.cfg
setup.py
kinetic/__init__.py
kinetic/admin.py
kinetic/baseasync.py
kinetic/baseclient.py
kinetic/batch.py
kinetic/common.py
kinetic/greenclient.py
kinetic/kinetic_pb2.py
kinetic/operations.py
kinetic/secureclient.py
kinetic/threadedclient.py
kinetic/utils.py
kinetic/zero_copy.py
kinetic.egg-info/PKG-INFO
kinetic.egg-info/SOURCES.txt
kinetic.egg-info/dependency_links.txt
kinetic.egg-info/entry_points.txt
kinetic.egg-info/requires.txt
kinetic.egg-info/top_level.txt
kinetic/cmd/__init__.py
kinetic/deprecated/__init__.py
kinetic/deprecated/adminclient.py
kinetic/deprecated/blockingclient.py
test/test_adminclient.py
test/test_batch.py
test/test_client.py
test/test_cmd.py
test/test_p2p.py