Metadata-Version: 1.1
Name: kinetic
Version: 0.9.1
Summary: Python client for Kinetic devices
Home-page: https://github.com/Seagate/kinetic-py
Author: Ignacio Corderi
Author-email: UNKNOWN
License: LGPLv2.1
Keywords: kinetic protocol api storage key/value seagate
Platform: UNKNOWN
Classifier: Development Status :: 4 - Beta
Classifier: Intended Audience :: Developers
Classifier: Intended Audience :: Information Technology
Classifier: License :: OSI Approved :: GNU Lesser General Public License v2 or later (LGPLv2+)
Classifier: Programming Language :: Python :: 2.7
Classifier: Programming Language :: Python :: 2 :: Only
Classifier: Topic :: Software Development :: Libraries :: Python Modules
Requires: protobuf
Requires: eventlet
